inte_dashboard/__init__.py
inte_dashboard/admin.py
inte_dashboard/apps.py
inte_dashboard/navbars.py
inte_dashboard/patterns.py
inte_dashboard/urls.py
inte_dashboard/migrations/__init__.py
inte_dashboard/model_wrappers/__init__.py
inte_dashboard/model_wrappers/ae_initial_model_wrapper.py
inte_dashboard/model_wrappers/death_report_model_wrapper.py
inte_dashboard/model_wrappers/subject_refusal_model_wrapper.py
inte_dashboard/model_wrappers/subject_screening_model_wrapper.py
inte_dashboard/templates/inte_dashboard/bootstrap3/buttons/add_consent_button.html
inte_dashboard/templates/inte_dashboard/bootstrap3/buttons/dashboard_button.html
inte_dashboard/templates/inte_dashboard/bootstrap3/buttons/eligibility_button.html
inte_dashboard/templates/inte_dashboard/bootstrap3/buttons/refusal_button.html
inte_dashboard/templates/inte_dashboard/bootstrap3/buttons/screening_button.html
inte_dashboard/templates/inte_dashboard/bootstrap3/screening/listboard.html
inte_dashboard/templates/inte_dashboard/bootstrap3/subject/dashboard.html
inte_dashboard/templates/inte_dashboard/bootstrap3/subject/listboard.html
inte_dashboard/templates/inte_dashboard/bootstrap3/subject/dashboard/top_bar.html
inte_dashboard/templatetags/__init__.py
inte_dashboard/templatetags/inte_dashboard_extras.py
inte_dashboard/tests/__init__.py
inte_dashboard/tests/admin.py
inte_dashboard/tests/urls.py
inte_dashboard/tests/tests/__init__.py
inte_dashboard/tests/tests/test_model_wrappers.py
inte_dashboard/views/__init__.py
inte_dashboard/views/ae/__init__.py
inte_dashboard/views/ae/ae_listboard_view.py
inte_dashboard/views/ae/death_report_listboard_view.py
inte_dashboard/views/screening/__init__.py
inte_dashboard/views/screening/filters.py
inte_dashboard/views/screening/listboard_view.py
inte_dashboard/views/subject/__init__.py
inte_dashboard/views/subject/dashboard/__init__.py
inte_dashboard/views/subject/dashboard/dashboard_view.py
inte_dashboard/views/subject/listboard/__init__.py
inte_dashboard-0.1.2.dist-info/AUTHORS
inte_dashboard-0.1.2.dist-info/LICENSE
inte_dashboard-0.1.2.dist-info/METADATA
inte_dashboard-0.1.2.dist-info/WHEEL
inte_dashboard-0.1.2.dist-info/top_level.txt
inte_dashboard-0.1.2.dist-info/RECORD
